{
	"design__io": 39,
	"design__die__area": 6309.99,
	"design__core__area": 3347.57,
	"design__instance__count": 202,
	"design__instance__area": 2444,
	"design__instance__count__stdcell": 202,
	"design__instance__area__stdcell": 2444,
	"design__instance__count__macros": 0,
	"design__instance__area__macros": 0,
	"design__instance__count__padcells": 0,
	"design__instance__area__padcells": 0,
	"design__instance__count__cover": 0,
	"design__instance__area__cover": 0,
	"design__instance__utilization": 0.730081,
	"design__instance__utilization__stdcell": 0.730081,
	"design__rows": 15,
	"design__rows:CoreSite": 15,
	"design__sites": 1845,
	"design__sites:CoreSite": 1845,
	"design__instance__count__class:timing_repair_buffer": 25,
	"design__instance__area__class:timing_repair_buffer": 321.149,
	"design__instance__count__class:inverter": 15,
	"design__instance__area__class:inverter": 99.792,
	"design__instance__count__class:sequential_cell": 9,
	"design__instance__area__class:sequential_cell": 444.528,
	"design__instance__count__class:multi_input_combinational_cell": 153,
	"design__instance__area__class:multi_input_combinational_cell": 1578.53,
	"design__instance__count": 202,
	"design__instance__area": 2444,
	"design__io": 39,
	"design__die__area": 6309.99,
	"design__core__area": 3347.57,
	"design__instance__count": 202,
	"design__instance__area": 2444,
	"design__instance__count__stdcell": 202,
	"design__instance__area__stdcell": 2444,
	"design__instance__count__macros": 0,
	"design__instance__area__macros": 0,
	"design__instance__count__padcells": 0,
	"design__instance__area__padcells": 0,
	"design__instance__count__cover": 0,
	"design__instance__area__cover": 0,
	"design__instance__utilization": 0.730081,
	"design__instance__utilization__stdcell": 0.730081,
	"design__rows": 15,
	"design__rows:CoreSite": 15,
	"design__sites": 1845,
	"design__sites:CoreSite": 1845,
	"flow__warnings__count": 4,
	"flow__errors__count": 0
}